LICENSE
README.md
setup.py
ipv4v6/__init__.py
ipv4v6/_core.py
ipv4v6.egg-info/PKG-INFO
ipv4v6.egg-info/SOURCES.txt
ipv4v6.egg-info/dependency_links.txt
ipv4v6.egg-info/requires.txt
ipv4v6.egg-info/top_level.txt