Metadata-Version: 2.1
Name: ipv4v6
Version: 1.1.0
Summary: A model for get ipv4&ipv6 address
Home-page: https://github.com/myhldh/GetIP
Author: OscarMYH(myhldh)
Author-email: oscarmyh@163.com
License: MIT
Keywords: python,computer vision,OscarMYH,myhldh,lightweight,windows,mac,linux
Classifier: Development Status :: 1 - Planning
Classifier: Intended Audience :: Developers
Classifier: Programming Language :: Python :: 3
Classifier: Operating System :: Unix
Classifier: Operating System :: MacOS :: MacOS X
Classifier: Operating System :: Microsoft :: Windows
License-File: LICENSE
Requires-Dist: requests
